mechanoChemML/__init__.py
mechanoChemML/src/LeastR.py
mechanoChemML/src/__init__.py
mechanoChemML/src/dictionary.py
mechanoChemML/src/estimator.py
mechanoChemML/src/gradient_layer.py
mechanoChemML/src/graph_functions.py
mechanoChemML/src/graph_main.py
mechanoChemML/src/graph_settings.py
mechanoChemML/src/graph_utilities.py
mechanoChemML/src/hparameters_cnn_grid.py
mechanoChemML/src/hparameters_dnn_grid.py
mechanoChemML/src/idnn.py
mechanoChemML/src/kbnn.py
mechanoChemML/src/kfold_train.py
mechanoChemML/src/load_dump.py
mechanoChemML/src/nn_models.py
mechanoChemML/src/pde_layers.py
mechanoChemML/src/stepwiseRegression.py
mechanoChemML/src/texify.py
mechanoChemML/src/transform_layer.py
mechanoChemML/testing/__init__.py
mechanoChemML/testing/idnn_convexity_test.py
mechanoChemML/workflows/__init__.py
mechanoChemML/workflows/active_learning/LSF_manager.py
mechanoChemML/workflows/active_learning/__init__.py
mechanoChemML/workflows/active_learning/active_learning.py
mechanoChemML/workflows/active_learning/data_generation_surrogate.py
mechanoChemML/workflows/active_learning/data_generation_wrapper.py
mechanoChemML/workflows/active_learning/hp_search.py
mechanoChemML/workflows/active_learning/monte_settings.json.tmpl
mechanoChemML/workflows/active_learning/optimize_hparameters.py
mechanoChemML/workflows/active_learning/save_weights.py
mechanoChemML/workflows/active_learning/slurm_manager.py
mechanoChemML/workflows/active_learning/surrogate_weights/bias_0.txt
mechanoChemML/workflows/active_learning/surrogate_weights/bias_1.txt
mechanoChemML/workflows/active_learning/surrogate_weights/bias_2.txt
mechanoChemML/workflows/active_learning/surrogate_weights/weights_0.txt
mechanoChemML/workflows/active_learning/surrogate_weights/weights_1.txt
mechanoChemML/workflows/active_learning/surrogate_weights/weights_2.txt
mechanoChemML/workflows/mr_learning/__init__.py
mechanoChemML/workflows/mr_learning/mrnn_models.py
mechanoChemML/workflows/mr_learning/mrnn_utility.py
mechanoChemML-0.1.1.dist-info/LICENSE.txt
mechanoChemML-0.1.1.dist-info/METADATA
mechanoChemML-0.1.1.dist-info/WHEEL
mechanoChemML-0.1.1.dist-info/top_level.txt
mechanoChemML-0.1.1.dist-info/RECORD
