Metadata-Version: 2.1
Name: mechanoChemML
Version: 0.1.1
Summary: A machine learning software library for computational materials physics
Home-page: https://github.com/mechanoChem/mechanoChemML
Author: Xiaoxuan Zhang
Author-email: zhangxiaoxuan258@gmail.com
License: UNKNOWN
Platform: UNKNOWN
Classifier: Programming Language :: Python :: 3.7
Classifier: License :: OSI Approved :: BSD License
License-File: LICENSE.txt
Requires-Dist: Sphinx (==1.8.1)
Requires-Dist: numpydoc (==0.9.2)
Requires-Dist: sphinx-rtd-theme (==0.4.3)
Requires-Dist: jinja2 (==3.0.3)
Requires-Dist: sphinx-autoapi
Requires-Dist: matplotlib
Requires-Dist: pandas
Requires-Dist: scikit-learn
Requires-Dist: natsort
Requires-Dist: keras
Requires-Dist: sobol-seq
Requires-Dist: vtk
Requires-Dist: SALib
Requires-Dist: seaborn
Requires-Dist: jupyter
Requires-Dist: six (>=1.16.0)
Requires-Dist: numexpr (>=2.8.0)
Requires-Dist: jsonpickle (>=2.1.0)
Requires-Dist: h5py (>=3.6.0)
Requires-Dist: dill (>=0.3.4)
Requires-Dist: sparse (>=0.13.0)
Requires-Dist: joblib (>=1.1.0)
Requires-Dist: progress (>=1.6)
Provides-Extra: dev
Requires-Dist: pytest (>=3.6) ; extra == 'dev'
